tweetscraper/__init__.py
tweetscraper/items.py
tweetscraper/pipelines.py
tweetscraper/settings.py
tweetscraper/utils.py
tweetscraper/spiders/__init__.py
tweetscraper/spiders/tweetcrawler.py
tweetscraper-1.2.6.dist-info/METADATA
tweetscraper-1.2.6.dist-info/RECORD
tweetscraper-1.2.6.dist-info/WHEEL
tweetscraper-1.2.6.dist-info/entry_points.txt
tweetscraper-1.2.6.dist-info/top_level.txt
